llmuses/__init__.py
llmuses/cache.py
llmuses/config.py
llmuses/constants.py
llmuses/run.py
llmuses/run_arena.py
llmuses/run_ms.py
llmuses/summarizer.py
llmuses/version.py
llmuses/backend/__init__.py
llmuses/backend/base.py
llmuses/backend/opencompass/__init__.py
llmuses/backend/opencompass/api_meta_template.py
llmuses/backend/opencompass/backend_manager.py
llmuses/backend/opencompass/tasks/__init__.py
llmuses/backend/opencompass/tasks/eval_api.py
llmuses/backend/opencompass/tasks/eval_datasets.py
llmuses/backend/vlm_eval_kit/__init__.py
llmuses/backend/vlm_eval_kit/backend_manager.py
llmuses/benchmarks/__init__.py
llmuses/benchmarks/benchmark.py
llmuses/benchmarks/data_adapter.py
llmuses/benchmarks/arc/__init__.py
llmuses/benchmarks/arc/ai2_arc.py
llmuses/benchmarks/arc/arc_adapter.py
llmuses/benchmarks/bbh/__init__.py
llmuses/benchmarks/bbh/bbh_adapter.py
llmuses/benchmarks/bbh/cot_prompts/boolean_expressions.txt
llmuses/benchmarks/bbh/cot_prompts/causal_judgement.txt
llmuses/benchmarks/bbh/cot_prompts/date_understanding.txt
llmuses/benchmarks/bbh/cot_prompts/disambiguation_qa.txt
llmuses/benchmarks/bbh/cot_prompts/dyck_languages.txt
llmuses/benchmarks/bbh/cot_prompts/formal_fallacies.txt
llmuses/benchmarks/bbh/cot_prompts/geometric_shapes.txt
llmuses/benchmarks/bbh/cot_prompts/hyperbaton.txt
llmuses/benchmarks/bbh/cot_prompts/logical_deduction_five_objects.txt
llmuses/benchmarks/bbh/cot_prompts/logical_deduction_seven_objects.txt
llmuses/benchmarks/bbh/cot_prompts/logical_deduction_three_objects.txt
llmuses/benchmarks/bbh/cot_prompts/movie_recommendation.txt
llmuses/benchmarks/bbh/cot_prompts/multistep_arithmetic_two.txt
llmuses/benchmarks/bbh/cot_prompts/navigate.txt
llmuses/benchmarks/bbh/cot_prompts/object_counting.txt
llmuses/benchmarks/bbh/cot_prompts/penguins_in_a_table.txt
llmuses/benchmarks/bbh/cot_prompts/reasoning_about_colored_objects.txt
llmuses/benchmarks/bbh/cot_prompts/ruin_names.txt
llmuses-0.4.3.dist-info/METADATA
llmuses-0.4.3.dist-info/WHEEL
llmuses-0.4.3.dist-info/entry_points.txt
llmuses-0.4.3.dist-info/top_level.txt
llmuses-0.4.3.dist-info/RECORD
