Metadata-Version: 2.1
Name: llmuses
Version: 0.4.3
Summary: Eval-Scope: Lightweight LLMs Evaluation Framework
Home-page: https://github.com/modelscope/eval-scope
Author: ModelScope team
Author-email: contact@modelscope.cn
License: UNKNOWN
Keywords: python,llm,evaluation
Platform: UNKNOWN
Classifier: Development Status :: 4 - Beta
Classifier: License :: OSI Approved :: Apache Software License
Classifier: Operating System :: OS Independent
Classifier: Programming Language :: Python :: 3
Classifier: Programming Language :: Python :: 3.8
Classifier: Programming Language :: Python :: 3.9
Classifier: Programming Language :: Python :: 3.10
Requires-Python: >=3.8
Requires-Dist: torch
Requires-Dist: absl-py
Requires-Dist: accelerate
Requires-Dist: cachetools
Requires-Dist: editdistance
Requires-Dist: jsonlines
Requires-Dist: matplotlib
Requires-Dist: modelscope[framework]
Requires-Dist: nltk
Requires-Dist: openai
Requires-Dist: pandas
Requires-Dist: plotly
Requires-Dist: pyarrow
Requires-Dist: pympler
Requires-Dist: pyyaml
Requires-Dist: regex
Requires-Dist: requests
Requires-Dist: requests-toolbelt
Requires-Dist: rouge-score
Requires-Dist: sacrebleu
Requires-Dist: scikit-learn
Requires-Dist: seaborn
Requires-Dist: sentencepiece
Requires-Dist: simple-ddl-parser
Requires-Dist: tabulate
Requires-Dist: tiktoken
Requires-Dist: tqdm
Requires-Dist: transformers (<4.43,>=4.33)
Requires-Dist: transformers-stream-generator
Requires-Dist: jieba
Requires-Dist: rouge-chinese
Provides-Extra: all
Requires-Dist: torch ; extra == 'all'
Requires-Dist: absl-py ; extra == 'all'
Requires-Dist: accelerate ; extra == 'all'
Requires-Dist: cachetools ; extra == 'all'
Requires-Dist: editdistance ; extra == 'all'
Requires-Dist: jsonlines ; extra == 'all'
Requires-Dist: matplotlib ; extra == 'all'
Requires-Dist: modelscope[framework] ; extra == 'all'
Requires-Dist: nltk ; extra == 'all'
Requires-Dist: openai ; extra == 'all'
Requires-Dist: pandas ; extra == 'all'
Requires-Dist: plotly ; extra == 'all'
Requires-Dist: pyarrow ; extra == 'all'
Requires-Dist: pympler ; extra == 'all'
Requires-Dist: pyyaml ; extra == 'all'
Requires-Dist: regex ; extra == 'all'
Requires-Dist: requests ; extra == 'all'
Requires-Dist: requests-toolbelt ; extra == 'all'
Requires-Dist: rouge-score ; extra == 'all'
Requires-Dist: sacrebleu ; extra == 'all'
Requires-Dist: scikit-learn ; extra == 'all'
Requires-Dist: seaborn ; extra == 'all'
Requires-Dist: sentencepiece ; extra == 'all'
Requires-Dist: simple-ddl-parser ; extra == 'all'
Requires-Dist: tabulate ; extra == 'all'
Requires-Dist: tiktoken ; extra == 'all'
Requires-Dist: tqdm ; extra == 'all'
Requires-Dist: transformers (<4.43,>=4.33) ; extra == 'all'
Requires-Dist: transformers-stream-generator ; extra == 'all'
Requires-Dist: jieba ; extra == 'all'
Requires-Dist: rouge-chinese ; extra == 'all'
Requires-Dist: ms-opencompass ; extra == 'all'
Requires-Dist: ms-vlmeval ; extra == 'all'
Provides-Extra: inner
Requires-Dist: absl-py ; extra == 'inner'
Requires-Dist: accelerate ; extra == 'inner'
Requires-Dist: alibaba-itag-sdk ; extra == 'inner'
Requires-Dist: dashscope ; extra == 'inner'
Requires-Dist: editdistance ; extra == 'inner'
Requires-Dist: jsonlines ; extra == 'inner'
Requires-Dist: nltk ; extra == 'inner'
Requires-Dist: openai ; extra == 'inner'
Requires-Dist: pandas (==1.5.3) ; extra == 'inner'
Requires-Dist: plotly ; extra == 'inner'
Requires-Dist: pyarrow ; extra == 'inner'
Requires-Dist: pyodps ; extra == 'inner'
Requires-Dist: pyyaml ; extra == 'inner'
Requires-Dist: regex ; extra == 'inner'
Requires-Dist: requests (==2.28.1) ; extra == 'inner'
Requires-Dist: requests-toolbelt (==0.10.1) ; extra == 'inner'
Requires-Dist: rouge-score ; extra == 'inner'
Requires-Dist: sacrebleu ; extra == 'inner'
Requires-Dist: scikit-learn ; extra == 'inner'
Requires-Dist: seaborn ; extra == 'inner'
Requires-Dist: simple-ddl-parser ; extra == 'inner'
Requires-Dist: streamlit ; extra == 'inner'
Requires-Dist: tqdm ; extra == 'inner'
Requires-Dist: transformers (<4.43,>=4.33) ; extra == 'inner'
Requires-Dist: transformers-stream-generator ; extra == 'inner'
Provides-Extra: opencompass
Requires-Dist: ms-opencompass ; extra == 'opencompass'
Provides-Extra: vlmeval
Requires-Dist: ms-vlmeval ; extra == 'vlmeval'
